{
    "taskDefinitionArn": "arn:aws:ecs:eu-west-3:533267216139:task-definition/vivektaskdef:1",
    "containerDefinitions": [
        {
            "name": "vivekscontainer",
            "image": "533267216139.dkr.ecr.eu-west-3.amazonaws.com/vivek2120:latest",
            "cpu": 0,
            "portMappings": [
                {
                    "name": "vivekscontainer-8081-tcp",
                    "containerPort": 8081,
                    "hostPort": 8081,
                    "protocol": "tcp",
                    "appProtocol": "http"
                }
            ],
            "essential": true,
            "environment": [],
            "environmentFiles": [],
            "mountPoints": [],
            "volumesFrom": [],
            "ulimits": [],
            "logConfiguration": {
                "logDriver": "awslogs",
                "options": {
                    "awslogs-group": "/ecs/vivektaskdef",
                    "awslogs-create-group": "true",
                    "awslogs-region": "eu-west-3",
                    "awslogs-stream-prefix": "ecs"
                },
                "secretOptions": []
            },
            "systemControls": []
        }
    ],
    "family": "vivektaskdef",
    "executionRoleArn": "arn:aws:iam::533267216139:role/ecsTaskExecutionRole",
    "networkMode": "awsvpc",
    "revision": 1,
    "volumes": [],
    "status": "ACTIVE",
    "requiresAttributes": [
        {
            "name": "com.amazonaws.ecs.capability.logging-driver.awslogs"
        },
        {
            "name": "ecs.capability.execution-role-awslogs"
        },
        {
            "name": "com.amazonaws.ecs.capability.ecr-auth"
        },
        {
            "name": "com.amazonaws.ecs.capability.docker-remote-api.1.19"
        },
        {
            "name": "ecs.capability.execution-role-ecr-pull"
        },
        {
            "name": "com.amazonaws.ecs.capability.docker-remote-api.1.18"
        },
        {
            "name": "ecs.capability.task-eni"
        },
        {
            "name": "com.amazonaws.ecs.capability.docker-remote-api.1.29"
        }
    ],
    "placementConstraints": [],
    "compatibilities": [
        "EC2",
        "FARGATE"
    ],
    "requiresCompatibilities": [
        "FARGATE"
    ],
    "cpu": "1024",
    "memory": "3072",
    "runtimePlatform": {
        "cpuArchitecture": "X86_64",
        "operatingSystemFamily": "LINUX"
    },
    "registeredAt": "2024-06-14T13:44:03.225Z",
    "registeredBy": "arn:aws:iam::533267216139:root",
    "tags": []
}
